[
    {
        "frame": "0.jpg",
        "Left Foot - Right Knee": 22.195239929857262
    },
    {
        "frame": "1.jpg",
        "Left Foot - Right Knee": 21.775119909596523
    },
    {
        "frame": "2.jpg",
        "Left Foot - Right Knee": 21.538357838771294
    },
    {
        "frame": "3.jpg",
        "Left Foot - Right Knee": 20.425128254447657
    },
    {
        "frame": "4.jpg",
        "Left Foot - Right Knee": 20.524600363906774
    },
    {
        "frame": "0.jpg",
        "Left Foot - Spine1": 43.128048653258325
    },
    {
        "frame": "0.jpg",
        "Left Foot - Spine1": 41.128048653258325
    },
    {
        "frame": "0.jpg",
        "Left Foot - Spine1": 43.128048653258325
    },
    {
        "frame": "0.jpg",
        "Left Foot - Spine1": 41.128048653258325
    }
]
